streamlit_mui_elements/__init__.py
streamlit_mui_elements/version.py
streamlit_mui_elements/core/__init__.py
streamlit_mui_elements/core/element.py
streamlit_mui_elements/core/elements.py
streamlit_mui_elements/core/exceptions.py
streamlit_mui_elements/core/render.py
streamlit_mui_elements/modules/__init__.py
streamlit_mui_elements/modules/datagrid.py
streamlit_mui_elements/modules/file_upload.py
streamlit_mui_elements/modules/mui.py
streamlit_mui_elements-0.1.0.dist-info/LICENSE
streamlit_mui_elements-0.1.0.dist-info/METADATA
streamlit_mui_elements-0.1.0.dist-info/WHEEL
streamlit_mui_elements-0.1.0.dist-info/top_level.txt
streamlit_mui_elements-0.1.0.dist-info/RECORD
