Metadata-Version: 2.1
Name: streamlit-mui-elements
Version: 0.1.0
Summary: A Streamlit component for Material-UI elements
Home-page: https://github.com/your_username/streamlit-mui-elements
Author: Tom Jose
Author-email: tomj0311@gmail.com
License: Apache 2.0
Classifier: Programming Language :: Python :: 3
Classifier: License :: OSI Approved :: Apache Software License
Classifier: Operating System :: OS Independent
Requires-Python: >=3.6
License-File: LICENSE
Requires-Dist: streamlit>=0.63
Provides-Extra: devel
Requires-Dist: wheel; extra == "devel"
